MANIFEST.in
README.md
setup.py
hehey_htemplate.egg-info/PKG-INFO
hehey_htemplate.egg-info/SOURCES.txt
hehey_htemplate.egg-info/dependency_links.txt
hehey_htemplate.egg-info/top_level.txt
htemplate/LICENSE
htemplate/README.md
htemplate/__init__.py
htemplate/utils.py
htemplate/view.py
htemplate/base/BaseTemplate.py
htemplate/base/Expression.py
htemplate/base/Filters.py
htemplate/base/MyTemplate.py
htemplate/base/TemplateCompiler.py
htemplate/base/TemplateContext.py
htemplate/base/__init__.py
htemplate/base/view.html
htemplate/context/__init__.py
htemplate/context/common.py
htemplate/filters/__init__.py
htemplate/filters/common.py
htemplate/filters/risk.py
htemplate/nodes/BaseNode.py
htemplate/nodes/FuncNode.py
htemplate/nodes/MainNode.py
htemplate/nodes/TagNode.py
htemplate/nodes/__init__.py
htemplate/tag/FormTag.py
htemplate/tag/HtmlTag.py
htemplate/tag/SysTag.py
htemplate/tag/Tag.py
htemplate/tag/__init__.py