Metadata-Version: 2.1
Name: hehey-htemplate
Version: 1.0.6
Summary: hehey-htemplate 是一个python 轻量的模板引擎,其主要特点有:易学,示例全,功能全面,html友好标签,编译速度快,易扩展与其他模板引擎对比,其简单易学,速度快(大概1000次编译,800 多毫秒),随时随地编写自己的标签库.
Home-page: https://gitee.com/chinahehe/hehey-htemplate
Author: hehe
Author-email: chinabluexfw@163.com
License: UNKNOWN
Platform: UNKNOWN
